{
  "success": true,
  "data": [
    {
      "ID": 464220,
      "post_author": "0",
      "post_date": "2025-02-06 01:35:25",
      "post_date_gmt": "2025-02-06 01:35:25",
      "post_content": "<p><p>ARODES (Adrian Rodriguez) is a Spanish DJ and producer who has quickly gained recognition in the global electronic music scene. Known for his deep, melodic, and atmospheric sound, ARODES has produced standout tracks like “Reborn,” “Lucy,” “Don’t Know,” and “Stronger Then Before,” earning praise for their emotive depth and intricate production.\r\n\r\n</p><p>In 2024, ARODES reached a milestone by remixing Camelphat’s “Turning Stones” alongside Josh Gigante and collaborating with Jan Blomqvist on “Destination Lost,” further elevating his profile. His tracks have garnered support from major names like Adriatique, Artbat, Bedouin, Black Coffee, Hernan Cattaneo, Rüfüs du Sol, and Vintage Culture.\r\n\r\n</p><p>ARODES also founded Unreleased Records in 2024, alongside his event brand Unreleased, providing a platform for his own music and emerging talents. He also partnered with Armada Records, expanding his global influence.\r\n\r\n</p><p>Performing at top festivals and venues such as Tomorrowland, Coachella, Ushuaïa, Hi Ibiza, and Brooklyn Mirage, ARODES is known for delivering high-energy, atmospheric sets. In summer 2024, his brand Unreleased secured residencies at Void Club (Mykonos) and Playa Soleil (Ibiza). Looking ahead, he’ll embark on a Latin America tour in winter 2024-25.\r\n\r\n</p><p>What sets ARODES apart is his ability to merge underground electronic elements with a crowd-pleasing energy. As he continues to grow his label and collaborate with top artists, ARODES is positioned to become a leading figure in the global electronic music scene.</p></p>",
      "post_title": "ARODES",
      "post_excerpt": "",
      "post_status": "publish",
      "comment_status": "closed",
      "ping_status": "closed",
      "post_password": "",
      "post_name": "arodes",
      "to_ping": "",
      "pinged": "",
      "post_modified": "2025-02-06 01:35:25",
      "post_modified_gmt": "2025-02-06 01:35:25",
      "post_content_filtered": "",
      "post_parent": 0,
      "guid": "https://www.insomniac.com/?post_type=artist&#038;p=464220",
      "menu_order": 0,
      "post_type": "artist",
      "post_mime_type": "",
      "comment_count": "0",
      "filter": "raw",
      "name": "ARODES",
      "hero_img_url": "https://d3vhc53cl8e8km.cloudfront.net/hello-staging/wp-content/uploads/2025/02/06013527/98f6ee9a-e42a-11ef-954e-0ecc81f4ee58-972x597.jpg",
      "small_img_url": "https://d3vhc53cl8e8km.cloudfront.net/hello-staging/wp-content/uploads/2025/02/06013527/98f6ee9a-e42a-11ef-954e-0ecc81f4ee58-150x150.jpg",
      "social_links": [
        {
          "service": "soundcloud",
          "url": "https://soundcloud.com/arodes10"
        },
        {
          "service": "instagram",
          "url": "https://www.instagram.com/arodes_ofc/"
        },
        {
          "service": "spotify",
          "url": "https://open.spotify.com/artist/4p2f8wUtltMAFuIJB4NR47"
        }
      ],
      "bio": "%3Cp%3E%3Cp%3EARODES%20%28Adrian%20Rodriguez%29%20is%20a%20Spanish%20DJ%20and%20producer%20who%20has%20quickly%20gained%20recognition%20in%20the%20global%20electronic%20music%20scene.%20Known%20for%20his%20deep%2C%20melodic%2C%20and%20atmospheric%20sound%2C%20ARODES%20has%20produced%20standout%20tracks%20like%20%E2%80%9CReborn%2C%E2%80%9D%20%E2%80%9CLucy%2C%E2%80%9D%20%E2%80%9CDon%E2%80%99t%20Know%2C%E2%80%9D%20and%20%E2%80%9CStronger%20Then%20Before%2C%E2%80%9D%20earning%20praise%20for%20their%20emotive%20depth%20and%20intricate%20production.%0D%0A%0D%0A%3C%2Fp%3E%3Cp%3EIn%202024%2C%20ARODES%20reached%20a%20milestone%20by%20remixing%20Camelphat%E2%80%99s%20%E2%80%9CTurning%20Stones%E2%80%9D%20alongside%20Josh%20Gigante%20and%20collaborating%20with%20Jan%20Blomqvist%20on%20%E2%80%9CDestination%20Lost%2C%E2%80%9D%20further%20elevating%20his%20profile.%20His%20tracks%20have%20garnered%20support%20from%20major%20names%20like%20Adriatique%2C%20Artbat%2C%20Bedouin%2C%20Black%20Coffee%2C%20Hernan%20Cattaneo%2C%20R%C3%BCf%C3%BCs%20du%20Sol%2C%20and%20Vintage%20Culture.%0D%0A%0D%0A%3C%2Fp%3E%3Cp%3EARODES%20also%20founded%20Unreleased%20Records%20in%202024%2C%20alongside%20his%20event%20brand%20Unreleased%2C%20providing%20a%20platform%20for%20his%20own%20music%20and%20emerging%20talents.%20He%20also%20partnered%20with%20Armada%20Records%2C%20expanding%20his%20global%20influence.%0D%0A%0D%0A%3C%2Fp%3E%3Cp%3EPerforming%20at%20top%20festivals%20and%20venues%20such%20as%20Tomorrowland%2C%20Coachella%2C%20Ushua%C3%AFa%2C%20Hi%20Ibiza%2C%20and%20Brooklyn%20Mirage%2C%20ARODES%20is%20known%20for%20delivering%20high-energy%2C%20atmospheric%20sets.%20In%20summer%202024%2C%20his%20brand%20Unreleased%20secured%20residencies%20at%20Void%20Club%20%28Mykonos%29%20and%20Playa%20Soleil%20%28Ibiza%29.%20Looking%20ahead%2C%20he%E2%80%99ll%20embark%20on%20a%20Latin%20America%20tour%20in%20winter%202024-25.%0D%0A%0D%0A%3C%2Fp%3E%3Cp%3EWhat%20sets%20ARODES%20apart%20is%20his%20ability%20to%20merge%20underground%20electronic%20elements%20with%20a%20crowd-pleasing%20energy.%20As%20he%20continues%20to%20grow%20his%20label%20and%20collaborate%20with%20top%20artists%2C%20ARODES%20is%20positioned%20to%20become%20a%20leading%20figure%20in%20the%20global%20electronic%20music%20scene.%3C%2Fp%3E%3C%2Fp%3E"
    }
  ]
}